panda_common_s-0.0.11.data/data/etc/panda/panda_common.cfg.rpmnew.template
panda_common_s-0.0.11.dist-info/METADATA
panda_common_s-0.0.11.dist-info/RECORD
panda_common_s-0.0.11.dist-info/WHEEL
panda_common_s-0.0.11.dist-info/top_level.txt
pandacommon/__init__.py
pandacommon/liveconfigparser/LiveConfigParser.py
pandacommon/liveconfigparser/__init__.py
pandacommon/pandalogger/LogWrapper.py
pandacommon/pandalogger/PandaLogger.py
pandacommon/pandalogger/__init__.py
pandacommon/pandalogger/logger_config.py
pandacommon/pandautils/ConfigUtils.py
pandacommon/pandautils/PandaUtils.py
pandacommon/pandautils/__init__.py
pandacommon/pandautils/utils_config.py
pandacommon/test/__init__.py
pandacommon/test/logtest.py
