Metadata-Version: 2.1
Name: panda-common-s
Version: 0.0.11
Summary: PanDA Common Package
Home-page: https://twiki.cern.ch/twiki/bin/view/Atlas/PanDA
Author: Panda Team
Author-email: atlas-adc-panda@cern.ch
License: GPL
Platform: UNKNOWN
Requires-Dist: configparser
Requires-Dist: future
